taichi_nightly_cuda_10_0-0.5.10.data/purelib/taichi/__init__.py
taichi_nightly_cuda_10_0-0.5.10.data/purelib/taichi/__main__.py
taichi_nightly_cuda_10_0-0.5.10.data/purelib/taichi/main.py
taichi_nightly_cuda_10_0-0.5.10.data/purelib/taichi/torch_io.py
taichi_nightly_cuda_10_0-0.5.10.data/purelib/taichi/core/__init__.py
taichi_nightly_cuda_10_0-0.5.10.data/purelib/taichi/core/unit.py
taichi_nightly_cuda_10_0-0.5.10.data/purelib/taichi/core/util.py
taichi_nightly_cuda_10_0-0.5.10.data/purelib/taichi/lang/__init__.py
taichi_nightly_cuda_10_0-0.5.10.data/purelib/taichi/lang/ast_checker.py
taichi_nightly_cuda_10_0-0.5.10.data/purelib/taichi/lang/core.py
taichi_nightly_cuda_10_0-0.5.10.data/purelib/taichi/lang/expr.py
taichi_nightly_cuda_10_0-0.5.10.data/purelib/taichi/lang/impl.py
taichi_nightly_cuda_10_0-0.5.10.data/purelib/taichi/lang/kernel.py
taichi_nightly_cuda_10_0-0.5.10.data/purelib/taichi/lang/kernel_arguments.py
taichi_nightly_cuda_10_0-0.5.10.data/purelib/taichi/lang/linalg.py
taichi_nightly_cuda_10_0-0.5.10.data/purelib/taichi/lang/matrix.py
taichi_nightly_cuda_10_0-0.5.10.data/purelib/taichi/lang/meta.py
taichi_nightly_cuda_10_0-0.5.10.data/purelib/taichi/lang/ndrange.py
taichi_nightly_cuda_10_0-0.5.10.data/purelib/taichi/lang/ops.py
taichi_nightly_cuda_10_0-0.5.10.data/purelib/taichi/lang/snode.py
taichi_nightly_cuda_10_0-0.5.10.data/purelib/taichi/lang/tape.py
taichi_nightly_cuda_10_0-0.5.10.data/purelib/taichi/lang/transformer.py
taichi_nightly_cuda_10_0-0.5.10.data/purelib/taichi/lang/util.py
taichi_nightly_cuda_10_0-0.5.10.data/purelib/taichi/lib/libdevice.10.bc
taichi_nightly_cuda_10_0-0.5.10.data/purelib/taichi/lib/runtime_cuda.bc
taichi_nightly_cuda_10_0-0.5.10.data/purelib/taichi/lib/runtime_x64.bc
taichi_nightly_cuda_10_0-0.5.10.data/purelib/taichi/lib/taichi_core.so
taichi_nightly_cuda_10_0-0.5.10.data/purelib/taichi/misc/__init__.py
taichi_nightly_cuda_10_0-0.5.10.data/purelib/taichi/misc/gui.py
taichi_nightly_cuda_10_0-0.5.10.dist-info/LICENSE.txt
taichi_nightly_cuda_10_0-0.5.10.dist-info/METADATA
taichi_nightly_cuda_10_0-0.5.10.dist-info/WHEEL
taichi_nightly_cuda_10_0-0.5.10.dist-info/entry_points.txt
taichi_nightly_cuda_10_0-0.5.10.dist-info/top_level.txt
taichi_nightly_cuda_10_0-0.5.10.dist-info/RECORD
